custom_tree/__init__.py
custom_tree/main.py
custom_tree-1.7.dist-info/LICENSE
custom_tree-1.7.dist-info/METADATA
custom_tree-1.7.dist-info/WHEEL
custom_tree-1.7.dist-info/entry_points.txt
custom_tree-1.7.dist-info/top_level.txt
custom_tree-1.7.dist-info/RECORD
