Metadata-Version: 2.1
Name: custom-tree
Version: 1.7
Summary: Creating a custom directory tree is an efficient method for visually organizing your project's directory structure, complete with detailed information. It provides a clear model of your project layout for easy reference and management.
Home-page: https://github.com/dragon-devs/custom-tree
Author: dragon-devs
Author-email: dragonfourtyseven@email.com
License: MIT
Classifier: Programming Language :: Python :: 3
Classifier: License :: OSI Approved :: MIT License
Classifier: Operating System :: OS Independent
License-File: LICENSE
